{
    "app-id" : "org.gnome.SoundRecorderDevel",
    "runtime" : "org.gnome.Platform",
    "runtime-version" : "master",
    "sdk" : "org.gnome.Sdk",
    "command" : "gnome-sound-recorder",
    "tags" : [
        "nightly"
    ],
    "desktop-file-name-prefix" : "(Nightly) ",
    "finish-args" : [
        "--share=ipc",
        "--socket=x11",
        "--socket=wayland",
        "--socket=pulseaudio",
        "--filesystem=xdg-run/dconf",
        "--filesystem=~/.config/dconf:ro",
        "--talk-name=ca.desrt.dconf",
        "--env=DCONF_USER_CONFIG_DIR=.config/dconf",
        "--filesystem=~/Recordings:create"
    ],
    "modules" : [
    	{
    		"name": "libhandy",
    		"buildsystem": "meson",
    		"config-opts": [
			"-Dexamples=false",
			"-Dglade_catalog=disabled",
			"-Dtests=false",
			"-Dvapi=false"
    		],
	    	"sources":[{
	    		"type": "git",
	    		"url": "https://source.puri.sm/Librem5/libhandy.git",
	    		"tag": "v0.0.10",
	    		"commit": "2d777677352d037b6f5cc24d9c1c8d9a74ac0ded"
	    	}]
    	},
        {
            "name" : "gnome-sound-recorder",
            "buildsystem": "meson",
            "config-opts": [
            	"-Dprofile=development"
            ],
            "sources" : [
                {
                    "type" : "git",
                    "url" : "https://gitlab.gnome.org/GNOME/gnome-sound-recorder.git"
                }
            ]
        }
    ]
}
